[
  {
    "ticker": "BRK-B",
    "name": "BRK-B",
    "market": "USA",
    "country": "--",
    "sector": "--",
    "price": 482.7,
    "currency": "USD",
    "high_52w": 516.85,
    "discount_52w": 6.6,
    "market_cap_mln": 1041113.4,
    "volume_k": 4783.9,
    "smi": -38.86,
    "smi_ema": -46.22,
    "zone": "Bearish",
    "signal": "Strong BUY",
    "eps_ttm": null,
    "sales_ttm_mln": 410522.0,
    "quick_ratio": null,
    "scanned_at": "2026-05-17T10:33:39.256070"
  },
  {
    "ticker": "PGR",
    "name": "PGR",
    "market": "USA",
    "country": "--",
    "sector": "--",
    "price": 199.73,
    "currency": "USD",
    "high_52w": 289.96,
    "discount_52w": 31.1,
    "market_cap_mln": 116709.5,
    "volume_k": 2863.7,
    "smi": -42.54,
    "smi_ema": -42.7,
    "zone": "OVERSOLD",
    "signal": "Strong BUY",
    "eps_ttm": null,
    "sales_ttm_mln": 87637.0,
    "quick_ratio": null,
    "scanned_at": "2026-05-17T10:33:39.431103"
  },
  {
    "ticker": "EL",
    "name": "EL",
    "market": "USA",
    "country": "--",
    "sector": "--",
    "price": 80.28,
    "currency": "USD",
    "high_52w": 121.64,
    "discount_52w": 34.0,
    "market_cap_mln": 29044.9,
    "volume_k": 4452.4,
    "smi": -36.74,
    "smi_ema": -47.46,
    "zone": "Bearish",
    "signal": "Strong BUY",
    "eps_ttm": null,
    "sales_ttm_mln": 14326.0,
    "quick_ratio": 0.92,
    "scanned_at": "2026-05-17T10:33:39.586269"
  },
  {
    "ticker": "SIBN",
    "name": "SIBN",
    "market": "USA",
    "country": "--",
    "sector": "--",
    "price": 14.16,
    "currency": "USD",
    "high_52w": 21.89,
    "discount_52w": 35.3,
    "market_cap_mln": 628.0,
    "volume_k": 729.8,
    "smi": -34.04,
    "smi_ema": -45.47,
    "zone": "Bearish",
    "signal": "Strong BUY",
    "eps_ttm": null,
    "sales_ttm_mln": 200.9,
    "quick_ratio": 7.21,
    "scanned_at": "2026-05-17T10:33:39.800128"
  },
  {
    "ticker": "NUAI",
    "name": "NUAI",
    "market": "USA",
    "country": "--",
    "sector": "--",
    "price": 4.88,
    "currency": "USD",
    "high_52w": 9.44,
    "discount_52w": 48.3,
    "market_cap_mln": 484.8,
    "volume_k": 4874.6,
    "smi": -29.87,
    "smi_ema": -39.64,
    "zone": "Bearish",
    "signal": "Strong BUY",
    "eps_ttm": null,
    "sales_ttm_mln": 0.9,
    "quick_ratio": 1.57,
    "scanned_at": "2026-05-17T10:33:40.503434"
  },
  {
    "ticker": "EE",
    "name": "EE",
    "market": "USA",
    "country": "--",
    "sector": "--",
    "price": 35.71,
    "currency": "USD",
    "high_52w": 43.17,
    "discount_52w": 17.3,
    "market_cap_mln": 1136.9,
    "volume_k": 484.9,
    "smi": -39.54,
    "smi_ema": -47.57,
    "zone": "Bearish",
    "signal": "Strong BUY",
    "eps_ttm": null,
    "sales_ttm_mln": 1228.3,
    "quick_ratio": 2.34,
    "scanned_at": "2026-05-17T10:33:40.871768"
  },
  {
    "ticker": "BJ",
    "name": "BJ",
    "market": "USA",
    "country": "--",
    "sector": "--",
    "price": 96.36,
    "currency": "USD",
    "high_52w": 120.08,
    "discount_52w": 19.8,
    "market_cap_mln": 12304.4,
    "volume_k": 1887.1,
    "smi": -29.86,
    "smi_ema": -32.95,
    "zone": "Bearish",
    "signal": "Strong BUY",
    "eps_ttm": null,
    "sales_ttm_mln": 21457.3,
    "quick_ratio": 0.16,
    "scanned_at": "2026-05-17T10:33:42.088679"
  },
  {
    "ticker": "MTA",
    "name": "MTA",
    "market": "USA",
    "country": "--",
    "sector": "--",
    "price": 6.81,
    "currency": "USD",
    "high_52w": 9.25,
    "discount_52w": 26.4,
    "market_cap_mln": 636.3,
    "volume_k": 492.6,
    "smi": -39.3,
    "smi_ema": -41.66,
    "zone": "Bearish",
    "signal": "Strong BUY",
    "eps_ttm": null,
    "sales_ttm_mln": 5.9,
    "quick_ratio": 0.93,
    "scanned_at": "2026-05-17T10:33:42.109516"
  },
  {
    "ticker": "CHKP",
    "name": "Check Point Software Technologi",
    "market": "USA",
    "country": "--",
    "sector": "--",
    "price": 124.03,
    "currency": "USD",
    "high_52w": 233.78,
    "discount_52w": 46.9,
    "market_cap_mln": 12902.6,
    "volume_k": 1488.7,
    "smi": -79.19,
    "smi_ema": -81.84,
    "zone": "OVERSOLD",
    "signal": "Strong BUY",
    "eps_ttm": null,
    "sales_ttm_mln": 2725.4,
    "quick_ratio": 2.05,
    "scanned_at": "2026-05-17T10:33:42.229094"
  },
  {
    "ticker": "MMM",
    "name": "3M Company",
    "market": "USA",
    "country": "United States",
    "sector": "Industrials",
    "price": 146.22,
    "currency": "USD",
    "high_52w": 177.41,
    "discount_52w": 17.6,
    "market_cap_mln": 76263.6,
    "volume_k": 3892.3,
    "smi": -55.05,
    "smi_ema": -55.8,
    "zone": "OVERSOLD",
    "signal": "Strong BUY",
    "eps_ttm": 5.19,
    "sales_ttm_mln": 24948.0,
    "quick_ratio": 1.33,
    "scanned_at": "2026-05-17T10:33:42.859966"
  },
  {
    "ticker": "CNCK",
    "name": "Coincheck Group N.V.",
    "market": "USA",
    "country": "Netherlands",
    "sector": "Financial Services",
    "price": 2.03,
    "currency": "USD",
    "high_52w": 9.31,
    "discount_52w": 78.2,
    "market_cap_mln": 275.9,
    "volume_k": 1015.8,
    "smi": -32.57,
    "smi_ema": -43.53,
    "zone": "Bearish",
    "signal": "Strong BUY",
    "eps_ttm": -0.09,
    "sales_ttm_mln": 383330.0,
    "quick_ratio": 1.07,
    "scanned_at": "2026-05-17T10:33:43.207947"
  },
  {
    "ticker": "THC",
    "name": "Tenet Healthcare Corporation",
    "market": "USA",
    "country": "United States",
    "sector": "Healthcare",
    "price": 196.66,
    "currency": "USD",
    "high_52w": 247.21,
    "discount_52w": 20.4,
    "market_cap_mln": 16939.7,
    "volume_k": 1245.7,
    "smi": -48.14,
    "smi_ema": -52.45,
    "zone": "OVERSOLD",
    "signal": "Strong BUY",
    "eps_ttm": 19.23,
    "sales_ttm_mln": 21310.0,
    "quick_ratio": 1.68,
    "scanned_at": "2026-05-17T10:33:43.706266"
  },
  {
    "ticker": "PDYN",
    "name": "Palladyne AI Corp.",
    "market": "USA",
    "country": "United States",
    "sector": "Technology",
    "price": 6.45,
    "currency": "USD",
    "high_52w": 13.0,
    "discount_52w": 50.4,
    "market_cap_mln": 304.7,
    "volume_k": 2402.1,
    "smi": -49.21,
    "smi_ema": -50.28,
    "zone": "OVERSOLD",
    "signal": "Strong BUY",
    "eps_ttm": -0.59,
    "sales_ttm_mln": 5.2,
    "quick_ratio": 9.22,
    "scanned_at": "2026-05-17T10:33:43.784404"
  },
  {
    "ticker": "RPD",
    "name": "Rapid7, Inc.",
    "market": "USA",
    "country": "United States",
    "sector": "Technology",
    "price": 6.5,
    "currency": "USD",
    "high_52w": 25.85,
    "discount_52w": 74.9,
    "market_cap_mln": 434.4,
    "volume_k": 2177.2,
    "smi": -16.33,
    "smi_ema": -37.54,
    "zone": "Bearish",
    "signal": "Strong BUY",
    "eps_ttm": 0.35,
    "sales_ttm_mln": 859.8,
    "quick_ratio": 1.28,
    "scanned_at": "2026-05-17T10:33:44.170580"
  },
  {
    "ticker": "CNH",
    "name": "CNH Industrial N.V.",
    "market": "USA",
    "country": "United Kingdom",
    "sector": "Industrials",
    "price": 10.43,
    "currency": "USD",
    "high_52w": 14.27,
    "discount_52w": 26.9,
    "market_cap_mln": 12932.7,
    "volume_k": 16300.5,
    "smi": -42.18,
    "smi_ema": -43.88,
    "zone": "OVERSOLD",
    "signal": "Strong BUY",
    "eps_ttm": 0.32,
    "sales_ttm_mln": 18095.0,
    "quick_ratio": 1.9,
    "scanned_at": "2026-05-17T10:33:44.267325"
  },
  {
    "ticker": "ASAN",
    "name": "Asana, Inc.",
    "market": "USA",
    "country": "United States",
    "sector": "Technology",
    "price": 6.2,
    "currency": "USD",
    "high_52w": 19.0,
    "discount_52w": 67.4,
    "market_cap_mln": 1476.1,
    "volume_k": 6556.7,
    "smi": -35.89,
    "smi_ema": -45.43,
    "zone": "Bearish",
    "signal": "Strong BUY",
    "eps_ttm": -0.8,
    "sales_ttm_mln": 790.8,
    "quick_ratio": 1.18,
    "scanned_at": "2026-05-17T10:33:44.729716"
  },
  {
    "ticker": "SJM",
    "name": "The J.M. Smucker Company",
    "market": "USA",
    "country": "United States",
    "sector": "Consumer Defensive",
    "price": 100.54,
    "currency": "USD",
    "high_52w": 119.39,
    "discount_52w": 15.8,
    "market_cap_mln": 10722.4,
    "volume_k": 2227.1,
    "smi": -32.14,
    "smi_ema": -42.63,
    "zone": "Bearish",
    "signal": "Strong BUY",
    "eps_ttm": -11.79,
    "sales_ttm_mln": 8726.1,
    "quick_ratio": 0.35,
    "scanned_at": "2026-05-17T10:33:46.077447"
  },
  {
    "ticker": "ESTC",
    "name": "Elastic N.V.",
    "market": "USA",
    "country": "Netherlands",
    "sector": "Technology",
    "price": 50.6,
    "currency": "USD",
    "high_52w": 96.07,
    "discount_52w": 47.3,
    "market_cap_mln": 5237.2,
    "volume_k": 2154.3,
    "smi": -24.41,
    "smi_ema": -40.16,
    "zone": "Bearish",
    "signal": "Strong BUY",
    "eps_ttm": -0.79,
    "sales_ttm_mln": 1483.3,
    "quick_ratio": 1.92,
    "scanned_at": "2026-05-17T10:33:46.275318"
  },
  {
    "ticker": "BAK",
    "name": "Braskem SA",
    "market": "USA",
    "country": "Brazil",
    "sector": "Basic Materials",
    "price": 4.9,
    "currency": "USD",
    "high_52w": 5.39,
    "discount_52w": 9.2,
    "market_cap_mln": 1952.6,
    "volume_k": 2834.2,
    "smi": -26.71,
    "smi_ema": -40.2,
    "zone": "Bearish",
    "signal": "Strong BUY",
    "eps_ttm": -4.56,
    "sales_ttm_mln": 70717.0,
    "quick_ratio": 0.5,
    "scanned_at": "2026-05-17T10:33:46.811566"
  },
  {
    "ticker": "EXK",
    "name": "Endeavour Silver Corporation",
    "market": "USA",
    "country": "Canada",
    "sector": "Basic Materials",
    "price": 9.81,
    "currency": "USD",
    "high_52w": 15.15,
    "discount_52w": 35.2,
    "market_cap_mln": 2904.4,
    "volume_k": 9896.5,
    "smi": -37.67,
    "smi_ema": -42.66,
    "zone": "Bearish",
    "signal": "Strong BUY",
    "eps_ttm": -0.06,
    "sales_ttm_mln": 467.5,
    "quick_ratio": 1.3,
    "scanned_at": "2026-05-17T10:33:47.144420"
  },
  {
    "ticker": "METC",
    "name": "Ramaco Resources, Inc.",
    "market": "USA",
    "country": "United States",
    "sector": "Basic Materials",
    "price": 14.51,
    "currency": "USD",
    "high_52w": 57.8,
    "discount_52w": 74.9,
    "market_cap_mln": 945.7,
    "volume_k": 1810.8,
    "smi": -38.37,
    "smi_ema": -48.76,
    "zone": "Bearish",
    "signal": "Strong BUY",
    "eps_ttm": -1.1,
    "sales_ttm_mln": 536.6,
    "quick_ratio": 4.66,
    "scanned_at": "2026-05-17T10:33:47.394671"
  },
  {
    "ticker": "CALM",
    "name": "Cal-Maine Foods, Inc.",
    "market": "USA",
    "country": "United States",
    "sector": "Consumer Defensive",
    "price": 76.88,
    "currency": "USD",
    "high_52w": 126.4,
    "discount_52w": 39.2,
    "market_cap_mln": 3642.3,
    "volume_k": 879.4,
    "smi": -58.16,
    "smi_ema": -58.18,
    "zone": "OVERSOLD",
    "signal": "Strong BUY",
    "eps_ttm": 14.37,
    "sales_ttm_mln": 4261.9,
    "quick_ratio": 5.42,
    "scanned_at": "2026-05-17T10:33:47.614687"
  },
  {
    "ticker": "EVGO",
    "name": "EVgo Inc.",
    "market": "USA",
    "country": "United States",
    "sector": "Consumer Cyclical",
    "price": 1.9,
    "currency": "USD",
    "high_52w": 5.18,
    "discount_52w": 63.3,
    "market_cap_mln": 595.8,
    "volume_k": 4336.0,
    "smi": -38.22,
    "smi_ema": -42.49,
    "zone": "Bearish",
    "signal": "Strong BUY",
    "eps_ttm": -0.34,
    "sales_ttm_mln": 384.1,
    "quick_ratio": 2.19,
    "scanned_at": "2026-05-17T10:33:48.166820"
  },
  {
    "ticker": "BSM",
    "name": "Black Stone Minerals, L.P.",
    "market": "USA",
    "country": "United States",
    "sector": "Energy",
    "price": 14.01,
    "currency": "USD",
    "high_52w": 15.49,
    "discount_52w": 9.6,
    "market_cap_mln": 2977.1,
    "volume_k": 455.6,
    "smi": -29.85,
    "smi_ema": -29.38,
    "zone": "Bearish",
    "signal": "Strong BUY",
    "eps_ttm": 1.27,
    "sales_ttm_mln": 422.3,
    "quick_ratio": 3.88,
    "scanned_at": "2026-05-17T10:33:48.305083"
  },
  {
    "ticker": "FICO",
    "name": "Fair Isaac Corporation",
    "market": "USA",
    "country": "United States",
    "sector": "Technology",
    "price": 1098.59,
    "currency": "USD",
    "high_52w": 2217.6,
    "discount_52w": 50.5,
    "market_cap_mln": 25477.3,
    "volume_k": 370.1,
    "smi": -38.24,
    "smi_ema": -46.62,
    "zone": "Bearish",
    "signal": "Strong BUY",
    "eps_ttm": 31.53,
    "sales_ttm_mln": 1990.9,
    "quick_ratio": 0.83,
    "scanned_at": "2026-05-17T10:33:48.526211"
  },
  {
    "ticker": "ALXO",
    "name": "ALX Oncology Holdings Inc.",
    "market": "USA",
    "country": "United States",
    "sector": "Healthcare",
    "price": 2.03,
    "currency": "USD",
    "high_52w": 2.66,
    "discount_52w": 23.7,
    "market_cap_mln": 273.2,
    "volume_k": 906.5,
    "smi": -21.75,
    "smi_ema": -31.09,
    "zone": "Bearish",
    "signal": "Strong BUY",
    "eps_ttm": -1.49,
    "sales_ttm_mln": 0.0,
    "quick_ratio": 2.07,
    "scanned_at": "2026-05-17T10:33:48.577344"
  },
  {
    "ticker": "UMAC",
    "name": "Unusual Machines, Inc.",
    "market": "USA",
    "country": "United States",
    "sector": "Technology",
    "price": 16.2,
    "currency": "USD",
    "high_52w": 23.38,
    "discount_52w": 30.7,
    "market_cap_mln": 774.3,
    "volume_k": 4449.7,
    "smi": -39.19,
    "smi_ema": -42.26,
    "zone": "Bearish",
    "signal": "Strong BUY",
    "eps_ttm": -0.32,
    "sales_ttm_mln": 11.2,
    "quick_ratio": 59.27,
    "scanned_at": "2026-05-17T10:33:49.301848"
  },
  {
    "ticker": "CLX",
    "name": "Clorox Company (The)",
    "market": "USA",
    "country": "United States",
    "sector": "Consumer Defensive",
    "price": 90.45,
    "currency": "USD",
    "high_52w": 136.69,
    "discount_52w": 33.8,
    "market_cap_mln": 10937.3,
    "volume_k": 2644.4,
    "smi": -73.73,
    "smi_ema": -74.48,
    "zone": "OVERSOLD",
    "signal": "Strong BUY",
    "eps_ttm": 6.15,
    "sales_ttm_mln": 7104.0,
    "quick_ratio": 0.57,
    "scanned_at": "2026-05-17T10:33:50.089598"
  },
  {
    "ticker": "ABBV",
    "name": "AbbVie Inc.",
    "market": "USA",
    "country": "United States",
    "sector": "Healthcare",
    "price": 210.39,
    "currency": "USD",
    "high_52w": 244.81,
    "discount_52w": 14.1,
    "market_cap_mln": 371715.5,
    "volume_k": 6771.0,
    "smi": -39.89,
    "smi_ema": -47.55,
    "zone": "Bearish",
    "signal": "Strong BUY",
    "eps_ttm": 2.04,
    "sales_ttm_mln": 61160.0,
    "quick_ratio": 0.56,
    "scanned_at": "2026-05-17T10:33:50.580531"
  },
  {
    "ticker": "TPB",
    "name": "Turning Point Brands, Inc.",
    "market": "USA",
    "country": "United States",
    "sector": "Consumer Defensive",
    "price": 89.56,
    "currency": "USD",
    "high_52w": 146.9,
    "discount_52w": 39.0,
    "market_cap_mln": 1734.6,
    "volume_k": 502.0,
    "smi": -34.77,
    "smi_ema": -47.11,
    "zone": "Bearish",
    "signal": "Strong BUY",
    "eps_ttm": 2.92,
    "sales_ttm_mln": 463.1,
    "quick_ratio": 4.12,
    "scanned_at": "2026-05-17T10:33:50.891825"
  },
  {
    "ticker": "COMP",
    "name": "Compass, Inc.",
    "market": "USA",
    "country": "United States",
    "sector": "Real Estate",
    "price": 7.88,
    "currency": "USD",
    "high_52w": 13.95,
    "discount_52w": 43.5,
    "market_cap_mln": 5887.6,
    "volume_k": 15318.4,
    "smi": -28.29,
    "smi_ema": -41.08,
    "zone": "Bearish",
    "signal": "Strong BUY",
    "eps_ttm": 0.02,
    "sales_ttm_mln": 6961.6,
    "quick_ratio": 0.86,
    "scanned_at": "2026-05-17T10:33:51.112083"
  },
  {
    "ticker": "NVAX",
    "name": "Novavax, Inc.",
    "market": "USA",
    "country": "United States",
    "sector": "Healthcare",
    "price": 9.06,
    "currency": "USD",
    "high_52w": 11.97,
    "discount_52w": 24.3,
    "market_cap_mln": 1489.8,
    "volume_k": 4650.5,
    "smi": -30.51,
    "smi_ema": -39.85,
    "zone": "Bearish",
    "signal": "Strong BUY",
    "eps_ttm": -0.56,
    "sales_ttm_mln": 1123.5,
    "quick_ratio": 2.1,
    "scanned_at": "2026-05-17T10:33:51.423147"
  },
  {
    "ticker": "SONY",
    "name": "Sony Group Corporation",
    "market": "USA",
    "country": "Japan",
    "sector": "Technology",
    "price": 22.31,
    "currency": "USD",
    "high_52w": 30.34,
    "discount_52w": 26.5,
    "market_cap_mln": 131808.8,
    "volume_k": 6125.5,
    "smi": -32.72,
    "smi_ema": -44.16,
    "zone": "Bearish",
    "signal": "Strong BUY",
    "eps_ttm": 1.09,
    "sales_ttm_mln": 12957064.0,
    "quick_ratio": 0.57,
    "scanned_at": "2026-05-17T10:33:51.549949"
  },
  {
    "ticker": "WLDN",
    "name": "Willdan Group, Inc.",
    "market": "USA",
    "country": "United States",
    "sector": "Industrials",
    "price": 92.12,
    "currency": "USD",
    "high_52w": 137.0,
    "discount_52w": 32.8,
    "market_cap_mln": 1392.0,
    "volume_k": 394.0,
    "smi": -22.56,
    "smi_ema": -44.42,
    "zone": "Bearish",
    "signal": "Strong BUY",
    "eps_ttm": 3.72,
    "sales_ttm_mln": 681.6,
    "quick_ratio": 1.56,
    "scanned_at": "2026-05-17T10:33:51.842643"
  },
  {
    "ticker": "SHMD",
    "name": "SCHMID Group N.V.",
    "market": "USA",
    "country": "Germany",
    "sector": "Industrials",
    "price": 6.87,
    "currency": "USD",
    "high_52w": 10.65,
    "discount_52w": 35.5,
    "market_cap_mln": 397.1,
    "volume_k": 881.7,
    "smi": -29.37,
    "smi_ema": -38.41,
    "zone": "Bearish",
    "signal": "Strong BUY",
    "eps_ttm": -1.07,
    "sales_ttm_mln": 60.8,
    "quick_ratio": 0.45,
    "scanned_at": "2026-05-17T10:33:52.159618"
  },
  {
    "ticker": "BBOT",
    "name": "BridgeBio Oncology Therapeutics",
    "market": "USA",
    "country": "United States",
    "sector": "Healthcare",
    "price": 8.51,
    "currency": "USD",
    "high_52w": 14.87,
    "discount_52w": 42.8,
    "market_cap_mln": 681.7,
    "volume_k": 326.4,
    "smi": -69.32,
    "smi_ema": -71.46,
    "zone": "OVERSOLD",
    "signal": "Strong BUY",
    "eps_ttm": -1.92,
    "sales_ttm_mln": 0.0,
    "quick_ratio": 12.34,
    "scanned_at": "2026-05-17T10:33:52.995985"
  },
  {
    "ticker": "FRMI",
    "name": "Fermi Inc.",
    "market": "USA",
    "country": "United States",
    "sector": "Real Estate",
    "price": 6.51,
    "currency": "USD",
    "high_52w": 36.99,
    "discount_52w": 82.4,
    "market_cap_mln": 4150.6,
    "volume_k": 14178.2,
    "smi": -62.67,
    "smi_ema": -68.29,
    "zone": "OVERSOLD",
    "signal": "Strong BUY",
    "eps_ttm": -1.13,
    "sales_ttm_mln": 0.0,
    "quick_ratio": 2.31,
    "scanned_at": "2026-05-17T10:33:53.120540"
  },
  {
    "ticker": "AG",
    "name": "First Majestic Silver Corp.",
    "market": "USA",
    "country": "Canada",
    "sector": "Basic Materials",
    "price": 20.42,
    "currency": "USD",
    "high_52w": 32.04,
    "discount_52w": 36.3,
    "market_cap_mln": 10082.8,
    "volume_k": 18542.2,
    "smi": -53.86,
    "smi_ema": -53.97,
    "zone": "OVERSOLD",
    "signal": "Strong BUY",
    "eps_ttm": 0.59,
    "sales_ttm_mln": 1265.2,
    "quick_ratio": 2.41,
    "scanned_at": "2026-05-17T10:33:53.228740"
  },
  {
    "ticker": "WDAY",
    "name": "Workday, Inc.",
    "market": "USA",
    "country": "United States",
    "sector": "Technology",
    "price": 125.01,
    "currency": "USD",
    "high_52w": 274.65,
    "discount_52w": 54.5,
    "market_cap_mln": 31213.2,
    "volume_k": 5405.0,
    "smi": -39.6,
    "smi_ema": -46.78,
    "zone": "Bearish",
    "signal": "Strong BUY",
    "eps_ttm": 2.59,
    "sales_ttm_mln": 9552.0,
    "quick_ratio": 1.32,
    "scanned_at": "2026-05-17T10:33:53.865990"
  },
  {
    "ticker": "CDRE",
    "name": "Cadre Holdings, Inc.",
    "market": "USA",
    "country": "United States",
    "sector": "Industrials",
    "price": 29.78,
    "currency": "USD",
    "high_52w": 48.76,
    "discount_52w": 38.9,
    "market_cap_mln": 1274.5,
    "volume_k": 427.3,
    "smi": -73.58,
    "smi_ema": -75.99,
    "zone": "OVERSOLD",
    "signal": "Strong BUY",
    "eps_ttm": 0.84,
    "sales_ttm_mln": 610.3,
    "quick_ratio": 2.54,
    "scanned_at": "2026-05-17T10:33:54.194079"
  },
  {
    "ticker": "USAS",
    "name": "Americas Gold and Silver Corpor",
    "market": "USA",
    "country": "Canada",
    "sector": "Basic Materials",
    "price": 6.25,
    "currency": "USD",
    "high_52w": 10.5,
    "discount_52w": 40.5,
    "market_cap_mln": 2036.8,
    "volume_k": 6350.8,
    "smi": -37.82,
    "smi_ema": -42.6,
    "zone": "Bearish",
    "signal": "Strong BUY",
    "eps_ttm": -0.33,
    "sales_ttm_mln": 117.9,
    "quick_ratio": 1.66,
    "scanned_at": "2026-05-17T10:33:54.735728"
  },
  {
    "ticker": "ASTS",
    "name": "AST SpaceMobile, Inc.",
    "market": "USA",
    "country": "United States",
    "sector": "Technology",
    "price": 83.67,
    "currency": "USD",
    "high_52w": 129.89,
    "discount_52w": 35.6,
    "market_cap_mln": 24996.1,
    "volume_k": 15700.5,
    "smi": -40.75,
    "smi_ema": -45.13,
    "zone": "OVERSOLD",
    "signal": "Strong BUY",
    "eps_ttm": -1.8,
    "sales_ttm_mln": 70.9,
    "quick_ratio": 16.27,
    "scanned_at": "2026-05-17T10:33:55.043824"
  },
  {
    "ticker": "NFGC",
    "name": "New Found Gold Corp",
    "market": "USA",
    "country": "Canada",
    "sector": "Basic Materials",
    "price": 2.02,
    "currency": "USD",
    "high_52w": 3.59,
    "discount_52w": 43.7,
    "market_cap_mln": 775.8,
    "volume_k": 1930.5,
    "smi": -35.7,
    "smi_ema": -41.77,
    "zone": "Bearish",
    "signal": "Strong BUY",
    "eps_ttm": -0.18,
    "sales_ttm_mln": 5.8,
    "quick_ratio": 3.48,
    "scanned_at": "2026-05-17T10:33:55.277050"
  },
  {
    "ticker": "RUN",
    "name": "Sunrun Inc.",
    "market": "USA",
    "country": "United States",
    "sector": "Technology",
    "price": 13.99,
    "currency": "USD",
    "high_52w": 22.44,
    "discount_52w": 37.7,
    "market_cap_mln": 3337.3,
    "volume_k": 10006.2,
    "smi": -26.26,
    "smi_ema": -39.37,
    "zone": "Bearish",
    "signal": "Strong BUY",
    "eps_ttm": 2.13,
    "sales_ttm_mln": 2957.0,
    "quick_ratio": 1.27,
    "scanned_at": "2026-05-17T10:33:56.200297"
  },
  {
    "ticker": "ENPH",
    "name": "Enphase Energy, Inc.",
    "market": "USA",
    "country": "United States",
    "sector": "Technology",
    "price": 52.89,
    "currency": "USD",
    "high_52w": 53.89,
    "discount_52w": 1.9,
    "market_cap_mln": 6970.8,
    "volume_k": 6403.6,
    "smi": -10.91,
    "smi_ema": -35.61,
    "zone": "Bearish",
    "signal": "Strong BUY",
    "eps_ttm": 1.01,
    "sales_ttm_mln": 1473.0,
    "quick_ratio": 1.84,
    "scanned_at": "2026-05-17T10:33:56.402019"
  },
  {
    "ticker": "CELH",
    "name": "Celsius Holdings, Inc.",
    "market": "USA",
    "country": "United States",
    "sector": "Consumer Defensive",
    "price": 30.16,
    "currency": "USD",
    "high_52w": 66.74,
    "discount_52w": 54.8,
    "market_cap_mln": 7710.1,
    "volume_k": 7766.2,
    "smi": -85.31,
    "smi_ema": -85.63,
    "zone": "OVERSOLD",
    "signal": "Strong BUY",
    "eps_ttm": 0.43,
    "sales_ttm_mln": 2515.3,
    "quick_ratio": 1.37,
    "scanned_at": "2026-05-17T10:33:57.676773"
  },
  {
    "ticker": "SCHW",
    "name": "Charles Schwab Corporation (The",
    "market": "USA",
    "country": "United States",
    "sector": "Financial Services",
    "price": 90.88,
    "currency": "USD",
    "high_52w": 107.5,
    "discount_52w": 15.5,
    "market_cap_mln": 158052.6,
    "volume_k": 10454.9,
    "smi": -64.65,
    "smi_ema": -65.05,
    "zone": "OVERSOLD",
    "signal": "Strong BUY",
    "eps_ttm": 5.03,
    "sales_ttm_mln": 23921.0,
    "quick_ratio": null,
    "scanned_at": "2026-05-17T10:33:57.948957"
  },
  {
    "ticker": "IBRX",
    "name": "ImmunityBio, Inc.",
    "market": "USA",
    "country": "United States",
    "sector": "Healthcare",
    "price": 7.97,
    "currency": "USD",
    "high_52w": 12.43,
    "discount_52w": 35.9,
    "market_cap_mln": 8347.4,
    "volume_k": 24682.0,
    "smi": -38.38,
    "smi_ema": -39.98,
    "zone": "Bearish",
    "signal": "Strong BUY",
    "eps_ttm": -0.85,
    "sales_ttm_mln": 113.3,
    "quick_ratio": 5.08,
    "scanned_at": "2026-05-17T10:33:58.160278"
  },
  {
    "ticker": "IVA",
    "name": "Inventiva S.A. - American Depos",
    "market": "USA",
    "country": "France",
    "sector": "Healthcare",
    "price": 5.44,
    "currency": "USD",
    "high_52w": 7.98,
    "discount_52w": 31.9,
    "market_cap_mln": 1129.6,
    "volume_k": 345.7,
    "smi": -59.49,
    "smi_ema": -60.9,
    "zone": "OVERSOLD",
    "signal": "Strong BUY",
    "eps_ttm": -2.23,
    "sales_ttm_mln": 4.5,
    "quick_ratio": 3.16,
    "scanned_at": "2026-05-17T10:33:58.254056"
  },
  {
    "ticker": "CL",
    "name": "Colgate-Palmolive Company",
    "market": "USA",
    "country": "United States",
    "sector": "Consumer Defensive",
    "price": 88.13,
    "currency": "USD",
    "high_52w": 99.33,
    "discount_52w": 11.3,
    "market_cap_mln": 70520.7,
    "volume_k": 5996.4,
    "smi": -32.21,
    "smi_ema": -40.86,
    "zone": "Bearish",
    "signal": "Strong BUY",
    "eps_ttm": 2.58,
    "sales_ttm_mln": 20382.0,
    "quick_ratio": null,
    "scanned_at": "2026-05-17T10:33:58.981830"
  },
  {
    "ticker": "SEPN",
    "name": "SEPN",
    "market": "USA",
    "country": "--",
    "sector": "--",
    "price": 26.95,
    "currency": "USD",
    "high_52w": 32.63,
    "discount_52w": 17.4,
    "market_cap_mln": 1214.8,
    "volume_k": 326.7,
    "smi": -50.72,
    "smi_ema": -57.68,
    "zone": "OVERSOLD",
    "signal": "Strong BUY",
    "eps_ttm": null,
    "sales_ttm_mln": null,
    "quick_ratio": null,
    "scanned_at": "2026-05-17T10:33:59.141804"
  }
]