[
  {
    "ticker": "RXRX",
    "name": "Recursion Pharmaceuticals, Inc.",
    "market": "USA",
    "country": "United States",
    "sector": "Healthcare",
    "price": 3.51,
    "currency": "USD",
    "smi": -25.03,
    "smi_ema": -40.5,
    "smi_above_ema": true,
    "zone": "Bearish",
    "signal": true,
    "strong_signal": true,
    "rev_prev": 5.0,
    "rev_curr": 35.4,
    "earn_prev": -162.3,
    "earn_curr": -108.1,
    "rev_yoy_pct": 683.7,
    "scanned_at": "2026-04-26T17:10:33.505706"
  },
  {
    "ticker": "SOUN",
    "name": "SoundHound AI, Inc.",
    "market": "USA",
    "country": "United States",
    "sector": "Technology",
    "price": 8.19,
    "currency": "USD",
    "smi": -27.2,
    "smi_ema": -46.62,
    "smi_above_ema": true,
    "zone": "Bearish",
    "signal": true,
    "strong_signal": true,
    "rev_prev": 42.0,
    "rev_curr": 55.1,
    "earn_prev": -109.3,
    "earn_curr": 40.1,
    "rev_yoy_pct": 59.4,
    "scanned_at": "2026-04-26T17:10:57.280644"
  },
  {
    "ticker": "AEBI",
    "name": "Aebi Schmidt Holding AG",
    "market": "USA",
    "country": "Switzerland",
    "sector": "Industrials",
    "price": 11.48,
    "currency": "USD",
    "smi": -38.26,
    "smi_ema": -45.27,
    "smi_above_ema": true,
    "zone": "Bearish",
    "signal": true,
    "strong_signal": true,
    "rev_prev": 471.3,
    "rev_curr": 528.4,
    "earn_prev": 1.2,
    "earn_curr": 8.8,
    "rev_yoy_pct": 77.2,
    "scanned_at": "2026-04-26T17:10:57.987614"
  },
  {
    "ticker": "FRD",
    "name": "Friedman Industries Inc.",
    "market": "USA",
    "country": "United States",
    "sector": "Basic Materials",
    "price": 20.52,
    "currency": "USD",
    "smi": -32.42,
    "smi_ema": -49.47,
    "smi_above_ema": true,
    "zone": "Bearish",
    "signal": true,
    "strong_signal": true,
    "rev_prev": 152.4,
    "rev_curr": 168.0,
    "earn_prev": 2.2,
    "earn_curr": 3.0,
    "rev_yoy_pct": 78.6,
    "scanned_at": "2026-04-26T17:11:51.086626"
  },
  {
    "ticker": "TTGT",
    "name": "TechTarget, Inc.",
    "market": "USA",
    "country": "United States",
    "sector": "Technology",
    "price": 5.65,
    "currency": "USD",
    "smi": -2.33,
    "smi_ema": -27.91,
    "smi_above_ema": true,
    "zone": "Bearish",
    "signal": true,
    "strong_signal": true,
    "rev_prev": 122.3,
    "rev_curr": 140.7,
    "earn_prev": -76.8,
    "earn_curr": -9.5,
    "rev_yoy_pct": 40.1,
    "scanned_at": "2026-04-26T17:11:59.634554"
  },
  {
    "ticker": "MFIN",
    "name": "Medallion Financial Corp.",
    "market": "USA",
    "country": "United States",
    "sector": "Financial Services",
    "price": 9.4,
    "currency": "USD",
    "smi": -24.04,
    "smi_ema": -39.29,
    "smi_above_ema": true,
    "zone": "Bearish",
    "signal": true,
    "strong_signal": true,
    "rev_prev": 55.9,
    "rev_curr": 67.6,
    "earn_prev": 11.3,
    "earn_curr": 12.2,
    "rev_yoy_pct": 25.4,
    "scanned_at": "2026-04-26T17:12:21.388385"
  },
  {
    "ticker": "ARQT",
    "name": "Arcutis Biotherapeutics, Inc.",
    "market": "USA",
    "country": "United States",
    "sector": "Healthcare",
    "price": 23.26,
    "currency": "USD",
    "smi": -38.07,
    "smi_ema": -45.41,
    "smi_above_ema": true,
    "zone": "Bearish",
    "signal": true,
    "strong_signal": true,
    "rev_prev": 99.2,
    "rev_curr": 129.5,
    "earn_prev": 7.4,
    "earn_curr": 17.4,
    "rev_yoy_pct": 81.5,
    "scanned_at": "2026-04-26T17:12:31.122675"
  },
  {
    "ticker": "TLSI",
    "name": "TriSalus Life Sciences, Inc.",
    "market": "USA",
    "country": "United States",
    "sector": "Healthcare",
    "price": 4.64,
    "currency": "USD",
    "smi": -27.19,
    "smi_ema": -41.2,
    "smi_above_ema": true,
    "zone": "Bearish",
    "signal": true,
    "strong_signal": true,
    "rev_prev": 11.6,
    "rev_curr": 13.2,
    "earn_prev": -10.8,
    "earn_curr": -9.8,
    "rev_yoy_pct": 59.8,
    "scanned_at": "2026-04-26T17:12:35.832006"
  },
  {
    "ticker": "RIGL",
    "name": "Rigel Pharmaceuticals, Inc.",
    "market": "USA",
    "country": "United States",
    "sector": "Healthcare",
    "price": 30.29,
    "currency": "USD",
    "smi": -30.82,
    "smi_ema": -46.23,
    "smi_above_ema": true,
    "zone": "Bearish",
    "signal": true,
    "strong_signal": true,
    "rev_prev": 69.5,
    "rev_curr": 69.8,
    "earn_prev": 27.9,
    "earn_curr": 268.1,
    "rev_yoy_pct": 21.2,
    "scanned_at": "2026-04-26T17:13:15.156258"
  },
  {
    "ticker": "XERS",
    "name": "Xeris Biopharma Holdings, Inc.",
    "market": "USA",
    "country": "United States",
    "sector": "Healthcare",
    "price": 6.05,
    "currency": "USD",
    "smi": -34.85,
    "smi_ema": -47.44,
    "smi_above_ema": true,
    "zone": "Bearish",
    "signal": true,
    "strong_signal": true,
    "rev_prev": 74.4,
    "rev_curr": 85.8,
    "earn_prev": 0.6,
    "earn_curr": 11.1,
    "rev_yoy_pct": 42.8,
    "scanned_at": "2026-04-26T17:13:41.057099"
  },
  {
    "ticker": "REAL",
    "name": "The RealReal, Inc.",
    "market": "USA",
    "country": "United States",
    "sector": "Consumer Cyclical",
    "price": 12.28,
    "currency": "USD",
    "smi": -26.43,
    "smi_ema": -47.21,
    "smi_above_ema": true,
    "zone": "Bearish",
    "signal": true,
    "strong_signal": true,
    "rev_prev": 173.6,
    "rev_curr": 194.1,
    "earn_prev": -54.1,
    "earn_curr": -38.8,
    "rev_yoy_pct": 18.3,
    "scanned_at": "2026-04-26T17:14:03.640157"
  },
  {
    "ticker": "GOLD",
    "name": "Gold.com, Inc.",
    "market": "USA",
    "country": "United States",
    "sector": "Financial Services",
    "price": 47.01,
    "currency": "USD",
    "smi": -42.13,
    "smi_ema": -43.5,
    "smi_above_ema": true,
    "zone": "OVERSOLD",
    "signal": true,
    "strong_signal": true,
    "rev_prev": 3680.8,
    "rev_curr": 6476.9,
    "earn_prev": -0.9,
    "earn_curr": 11.6,
    "rev_yoy_pct": 136.2,
    "scanned_at": "2026-04-26T17:14:16.087571"
  },
  {
    "ticker": "FIBK",
    "name": "First Interstate BancSystem, In",
    "market": "USA",
    "country": "United States",
    "sector": "Financial Services",
    "price": 34.85,
    "currency": "USD",
    "smi": -29.84,
    "smi_ema": -38.32,
    "smi_above_ema": true,
    "zone": "Bearish",
    "signal": true,
    "strong_signal": true,
    "rev_prev": 250.5,
    "rev_curr": 313.0,
    "earn_prev": 71.4,
    "earn_curr": 108.8,
    "rev_yoy_pct": 19.8,
    "scanned_at": "2026-04-26T17:15:13.525360"
  }
]