[
  {
    "ticker": "YELP",
    "name": "Yelp Inc.",
    "country": "United States",
    "sector": "Communication Services",
    "price": 24.52,
    "currency": "USD",
    "high_52w": 35.53,
    "discount_52w": 31.0,
    "market_cap_mln": 1348.4,
    "volume_k": 1240.4,
    "eps_ttm": 2.18,
    "sales_ttm_mln": 1465.0,
    "quick_ratio": 2.99,
    "roic": 0.2309,
    "debt_equity": 0.035,
    "gross_margin": 0.9027,
    "eps_q0": 0.3,
    "eps_q1": 0.61,
    "eps_q4": 0.36,
    "eps_qoq": -50.8,
    "eps_yoy": -16.7,
    "scanned_at": "2026-07-01T09:22:51.865592",
    "market": "USA",
    "smi": -34.29,
    "smi_ema": -36.99,
    "zone": "Bearish",
    "signal": "Strong BUY",
    "divergence_bull": false,
    "divergence_desc": "",
    "vol_confirm": false,
    "rs_12m": null,
    "wyckoff_score": 0,
    "wyckoff_phase": "–",
    "wyckoff_dist": false,
    "wyckoff_dsig": [],
    "d1_signal_now": false,
    "d1_zone_now": "OVERBOUGHT",
    "d1_last_cross_days_ago": 3,
    "early_signal": false,
    "tech_score": 9,
    "m_zone": "--",
    "m_bullish": false,
    "m_risk_warning": false,
    "mtf_score": 1
  }
]